derive_client/__init__.py
derive_client/_bridge/__init__.py
derive_client/_bridge/_derive_bridge.py
derive_client/_bridge/_standard_bridge.py
derive_client/_bridge/async_client.py
derive_client/_bridge/client.py
derive_client/_bridge/w3.py
derive_client/_clients/__init__.py
derive_client/_clients/rest/__init__.py
derive_client/_clients/rest/async_http/__init__.py
derive_client/_clients/rest/async_http/account.py
derive_client/_clients/rest/async_http/api.py
derive_client/_clients/rest/async_http/client.py
derive_client/_clients/rest/async_http/collateral.py
derive_client/_clients/rest/async_http/markets.py
derive_client/_clients/rest/async_http/mmp.py
derive_client/_clients/rest/async_http/orders.py
derive_client/_clients/rest/async_http/positions.py
derive_client/_clients/rest/async_http/rfq.py
derive_client/_clients/rest/async_http/session.py
derive_client/_clients/rest/async_http/subaccount.py
derive_client/_clients/rest/async_http/trades.py
derive_client/_clients/rest/async_http/transactions.py
derive_client/_clients/rest/endpoints.py
derive_client/_clients/rest/http/__init__.py
derive_client/_clients/rest/http/account.py
derive_client/_clients/rest/http/api.py
derive_client/_clients/rest/http/client.py
derive_client/_clients/rest/http/collateral.py
derive_client/_clients/rest/http/markets.py
derive_client/_clients/rest/http/mmp.py
derive_client/_clients/rest/http/orders.py
derive_client/_clients/rest/http/positions.py
derive_client/_clients/rest/http/rfq.py
derive_client/_clients/rest/http/session.py
derive_client/_clients/rest/http/subaccount.py
derive_client/_clients/rest/http/trades.py
derive_client/_clients/rest/http/transactions.py
derive_client/_clients/utils.py
derive_client/_clients/websockets/__init__.py
derive_client/_clients/websockets/api.py
derive_client/_clients/websockets/client.py
derive_client/_clients/websockets/session.py
derive_client/cli/__init__.py
derive_client/cli/_account.py
derive_client/cli/_bridge.py
derive_client/cli/_collateral.py
derive_client-0.3.11.dist-info/METADATA
derive_client-0.3.11.dist-info/WHEEL
derive_client-0.3.11.dist-info/entry_points.txt
derive_client-0.3.11.dist-info/RECORD
