Metadata-Version: 2.4
Name: derive-client
Version: 0.3.11
Summary: 
Author: 8baller
Author-email: 8baller@station.codes
Requires-Python: >=3.10,<3.14
Classifier: Programming Language :: Python :: 3
Classifier: Programming Language :: Python :: 3.10
Classifier: Programming Language :: Python :: 3.11
Classifier: Programming Language :: Python :: 3.12
Classifier: Programming Language :: Python :: 3.13
Requires-Dist: aiolimiter (>=1.2.1,<2.0.0)
Requires-Dist: derive-action-signing (>=0.0.13,<0.0.14)
Requires-Dist: msgspec (>=0.19.0,<0.20.0)
Requires-Dist: numpy (>2,<3)
Requires-Dist: pandas (>=1,<=3)
Requires-Dist: py-vollib (>=1.0.1,<2.0.0)
Requires-Dist: pydantic (>=2.11.3,<3.0.0)
Requires-Dist: python-dotenv (>=0.14.0,<2)
Requires-Dist: pyyaml (>=6.0.1)
Requires-Dist: requests (>=2,<3)
Requires-Dist: returns (>=0.26.0,<0.27.0)
Requires-Dist: rich-click (>=1.7.1,<2.0.0)
Requires-Dist: setuptools (>=68.2.2,<80)
Requires-Dist: web3 (>=7.14.0,<8.0.0)
